hexagonal_permutation_cipher/__init__.py
hexagonal_permutation_cipher/__main__.py
hexagonal_permutation_cipher/aes.py
hexagonal_permutation_cipher/benchmark.py
hexagonal_permutation_cipher/encryption.py
hexagonal_permutation_cipher/grid.py
hexagonal_permutation_cipher/utils.py
hexagonal_permutation_cipher/visualization.py
hexagonal_permutation_cipher/visualization_3d.py
Hexagonal_Permutation_Cipher-1.0.0.dist-info/METADATA
Hexagonal_Permutation_Cipher-1.0.0.dist-info/WHEEL
Hexagonal_Permutation_Cipher-1.0.0.dist-info/entry_points.txt
Hexagonal_Permutation_Cipher-1.0.0.dist-info/top_level.txt
Hexagonal_Permutation_Cipher-1.0.0.dist-info/RECORD
